MANIFEST.in
README
pyproject.toml
setup.py
src/onnx2akida/__init__.py
src/onnx2akida/cli.py
src/onnx2akida/compatibility_info.py
src/onnx2akida/convert.py
src/onnx2akida/hybrid_model.py
src/onnx2akida/version.py
src/onnx2akida.egg-info/PKG-INFO
src/onnx2akida.egg-info/SOURCES.txt
src/onnx2akida.egg-info/dependency_links.txt
src/onnx2akida.egg-info/entry_points.txt
src/onnx2akida.egg-info/requires.txt
src/onnx2akida.egg-info/top_level.txt
src/onnx2akida/inference/__init__.py
src/onnx2akida/inference/inference.py
src/onnx2akida/inference/ops.py
src/onnx2akida/pipeline/__init__.py
src/onnx2akida/pipeline/convert_to_hybrid.py
src/onnx2akida/pipeline/quantize.py
src/onnx2akida/pipeline/sequences.py
src/onnx2akida/tools/__init__.py
src/onnx2akida/tools/compose.py
src/onnx2akida/tools/context.py
src/onnx2akida/tools/node_utils.py
src/onnx2akida/transforms/__init__.py
src/onnx2akida/transforms/custom_patterns.py
src/onnx2akida/transforms/remove_pointless_quantizers.py