Metadata-Version: 2.4
Name: onnx2akida
Version: 0.6.0
Summary: Evaluates the compatibility of an ONNX model with Akida.
Author: Brainchip
Maintainer-email: Johan Mejia <jmejia@brainchip.com>
License-Expression: Apache-2.0
Project-URL: Documentation, https://doc.brainchipinc.com
Requires-Python: >=3.10
Requires-Dist: setuptools>=77.0.3
Requires-Dist: packaging>=24.2
Requires-Dist: setuptools_scm
Requires-Dist: cnn2snn~=2.18.1
Requires-Dist: tqdm
Provides-Extra: test
Requires-Dist: pytest; extra == "test"
Requires-Dist: pytest-console-scripts; extra == "test"
